{
  "title": {
    "EN": "Async Traits: The Hard Parts",
    "ES": "Async Traits: Las Partes Difíciles"
  },
  "content": "{\"EN\":\"Understanding why async traits were hard to implement and how the new return position impl Trait solves it.\",\"ES\":\"Entendiendo por qué los traits asíncronos fueron difíciles de implementar y cómo la nueva posición de retorno impl Trait lo resuelve.\"}",
  "image_url": "https://placehold.co/600x400/1F1F1F/CE412B/png?text=Async+Traits",
  "published_at": "2024-05-15T00:00:00.000Z",
  "tags": [
    "Deep Dive"
  ]
}